ilp_keyboard_layout_optimization/__init__.py
ilp_keyboard_layout_optimization/costs.py
ilp_keyboard_layout_optimization/ilp.py
ilp_keyboard_layout_optimization/optimize.py
ilp_keyboard_layout_optimization/type_aliases.py
ilp_keyboard_layout_optimization/visualize.py
ilp_keyboard_layout_optimization/data_aquisition/__init__.py
ilp_keyboard_layout_optimization/data_aquisition/chars.py
ilp_keyboard_layout_optimization/data_aquisition/positions.py
ilp_keyboard_layout_optimization/data_aquisition/probabilities.py
ilp_keyboard_layout_optimization-0.0.3.dist-info/METADATA
ilp_keyboard_layout_optimization-0.0.3.dist-info/WHEEL
ilp_keyboard_layout_optimization-0.0.3.dist-info/top_level.txt
ilp_keyboard_layout_optimization-0.0.3.dist-info/RECORD
