Metadata-Version: 2.1
Name: ilp-keyboard-layout-optimization
Version: 0.0.3
Summary: The QAP variant of keyboard layout optimization, i.e. character to key assignments
Home-page: https://git.tu-berlin.de/blutub3d/ilp_keyboard_layout_optimization
Author: Björn Ludwig
Author-email: bjoern.ludwig@campus.tu-berlin.de
License: MIT
Keywords: ilp,qap,keyboard layout optimization
Platform: UNKNOWN
Classifier: Development Status :: 2 - Pre-Alpha
Classifier: Intended Audience :: Education
Classifier: Intended Audience :: Science/Research
Classifier: License :: OSI Approved :: MIT License
Classifier: Natural Language :: English
Classifier: Operating System :: POSIX :: Linux
Classifier: Programming Language :: Python :: 3
Classifier: Programming Language :: Python :: 3.10
Classifier: Programming Language :: Python :: 3.11
Classifier: Topic :: Scientific/Engineering
Classifier: Topic :: Scientific/Engineering :: Mathematics
Classifier: Topic :: Scientific/Engineering :: Information Analysis
Classifier: Topic :: Scientific/Engineering :: Information Analysis
Classifier: Typing :: Typed
Requires-Python: >=3.10
Requires-Dist: pyscipopt
Provides-Extra: test
Requires-Dist: hypothesis ; extra == 'test'
Requires-Dist: pytest ; extra == 'test'
